Workbook

Sheet VENTES
A1: Code | B1: Médicament | C1: Catégorie | D1: Fournisseur | E1: Qté vendue | F1: Prix unitaire | G1: Semaine | H1: CA | I1: Marge brute | J1: Statut stock | K1: Référence interne | L1: Tendance
A2: MED001 | B2: Paracétamol 500mg | C2: Analgésique | D2: LABOREX | E2: 340 | F2: 250 | G2: S1 | H2: =VENTES!$E2*VENTES!$F2 -> 85000 | I2: =IF(C2="Antipaludéen",H2*30%,IF(C2="Antibiotique",H2*25%,H2*20%)) -> 17000 | J2: =IF(AND(E2>250,OR(D2="LABOREX",D2="COPHARMA")),"RÉAPPROVISIONNEMENT",IF(AND(E2>=150,E2<=250),"SURVEILLER","OK")) -> RÉAPPROVISIONNEMENT | K2: =IFERROR(LEFT(UPPER(C2),3)&"/"&LEFT(A2,4)&"/"&LEFT(UPPER(D2),3),"ERR") -> ANA/MED0/LAB
A3: MED002 | B3: Amoxicilline 250mg | C3: Antibiotique | D3: COPHARMED | E3: 120 | F3: 1800 | G3: S1 | H3: =VENTES!$E3*VENTES!$F3 -> 216000 | I3: =IF(C3="Antipaludéen",H3*30%,IF(C3="Antibiotique",H3*25%,H3*20%)) -> 54000 | J3: =IF(AND(E3>250,OR(D3="LABOREX",D3="COPHARMA")),"RÉAPPROVISIONNEMENT",IF(AND(E3>=150,E3<=250),"SURVEILLER","OK")) -> OK | K3: =IFERROR(LEFT(UPPER(C3),3)&"/"&LEFT(A3,4)&"/"&LEFT(UPPER(D3),3),"ERR") -> ANT/MED0/COP
A4: MED003 | B4: Arteméter-Luméfantrine | C4: Antipaludéen | D4: LABOREX | E4: 280 | F4: 2500 | G4: S1 | H4: =VENTES!$E4*VENTES!$F4 -> 700000 | I4: =IF(C4="Antipaludéen",H4*30%,IF(C4="Antibiotique",H4*25%,H4*20%)) -> 210000 | J4: =IF(AND(E4>250,OR(D4="LABOREX",D4="COPHARMA")),"RÉAPPROVISIONNEMENT",IF(AND(E4>=150,E4<=250),"SURVEILLER","OK")) -> RÉAPPROVISIONNEMENT | K4: =IFERROR(LEFT(UPPER(C4),3)&"/"&LEFT(A4,4)&"/"&LEFT(UPPER(D4),3),"ERR") -> ANT/MED0/LAB | V4: formule pour calculé
A5: MED004 | B5: Métronidazole 250mg | C5: Antibiotique | D5: BIOPHARMA | E5: 95 | F5: 900 | G5: S2 | H5: =VENTES!$E5*VENTES!$F5 -> 85500 | I5: =IF(C5="Antipaludéen",H5*30%,IF(C5="Antibiotique",H5*25%,H5*20%)) -> 21375 | J5: =IF(AND(E5>250,OR(D5="LABOREX",D5="COPHARMA")),"RÉAPPROVISIONNEMENT",IF(AND(E5>=150,E5<=250),"SURVEILLER","OK")) -> OK | K5: =IFERROR(LEFT(UPPER(C5),3)&"/"&LEFT(A5,4)&"/"&LEFT(UPPER(D5),3),"ERR") -> ANT/MED0/BIO
A6: MED005 | B6: Vitamine C 1000mg | C6: Complément | D6: COPHARMED | E6: 410 | F6: 350 | G6: S2 | H6: =VENTES!$E6*VENTES!$F6 -> 143500 | I6: =IF(C6="Antipaludéen",H6*30%,IF(C6="Antibiotique",H6*25%,H6*20%)) -> 28700 | J6: =IF(AND(E6>250,OR(D6="LABOREX",D6="COPHARMA")),"RÉAPPROVISIONNEMENT",IF(AND(E6>=150,E6<=250),"SURVEILLER","OK")) -> OK | K6: =IFERROR(LEFT(UPPER(C6),3)&"/"&LEFT(A6,4)&"/"&LEFT(UPPER(D6),3),"ERR") -> COM/MED0/COP
A7: MED006 | B7: Oméprazole 20mg | C7: Gastro | D7: BIOPHARMA | E7: 180 | F7: 1200 | G7: S2 | H7: =VENTES!$E7*VENTES!$F7 -> 216000 | I7: =IF(C7="Antipaludéen",H7*30%,IF(C7="Antibiotique",H7*25%,H7*20%)) -> 43200 | J7: =IF(AND(E7>250,OR(D7="LABOREX",D7="COPHARMA")),"RÉAPPROVISIONNEMENT",IF(AND(E7>=150,E7<=250),"SURVEILLER","OK")) -> SURVEILLER | K7: =IFERROR(LEFT(UPPER(C7),3)&"/"&LEFT(A7,4)&"/"&LEFT(UPPER(D7),3),"ERR") -> GAS/MED0/BIO
A8: MED007 | B8: Arteméter-Luméfantrine | C8: Antipaludéen | D8: LABOREX | E8: 320 | F8: 2500 | G8: S3 | H8: =VENTES!$E8*VENTES!$F8 -> 800000 | I8: =IF(C8="Antipaludéen",H8*30%,IF(C8="Antibiotique",H8*25%,H8*20%)) -> 240000 | J8: =IF(AND(E8>250,OR(D8="LABOREX",D8="COPHARMA")),"RÉAPPROVISIONNEMENT",IF(AND(E8>=150,E8<=250),"SURVEILLER","OK")) -> RÉAPPROVISIONNEMENT | K8: =IFERROR(LEFT(UPPER(C8),3)&"/"&LEFT(A8,4)&"/"&LEFT(UPPER(D8),3),"ERR") -> ANT/MED0/LAB
A9: MED008 | B9: Paracétamol 500mg | C9: Analgésique | D9: LABOREX | E9: 290 | F9: 250 | G9: S3 | H9: =VENTES!$E9*VENTES!$F9 -> 72500 | I9: =IF(C9="Antipaludéen",H9*30%,IF(C9="Antibiotique",H9*25%,H9*20%)) -> 14500 | J9: =IF(AND(E9>250,OR(D9="LABOREX",D9="COPHARMA")),"RÉAPPROVISIONNEMENT",IF(AND(E9>=150,E9<=250),"SURVEILLER","OK")) -> RÉAPPROVISIONNEMENT | K9: =IFERROR(LEFT(UPPER(C9),3)&"/"&LEFT(A9,4)&"/"&LEFT(UPPER(D9),3),"ERR") -> ANA/MED0/LAB
A10: MED009 | B10: Ibuprofène 400mg | C10: Analgésique | D10: COPHARMED | E10: 155 | F10: 700 | G10: S3 | H10: =VENTES!$E10*VENTES!$F10 -> 108500 | I10: =IF(C10="Antipaludéen",H10*30%,IF(C10="Antibiotique",H10*25%,H10*20%)) -> 21700 | J10: =IF(AND(E10>250,OR(D10="LABOREX",D10="COPHARMA")),"RÉAPPROVISIONNEMENT",IF(AND(E10>=150,E10<=250),"SURVEILLER","OK")) -> SURVEILLER | K10: =IFERROR(LEFT(UPPER(C10),3)&"/"&LEFT(A10,4)&"/"&LEFT(UPPER(D10),3),"ERR") -> ANA/MED0/COP
A11: MED010 | B11: Amoxicilline 250mg | C11: Antibiotique | D11: BIOPHARMA | E11: 200 | F11: 2200 | G11: S4 | H11: =VENTES!$E11*VENTES!$F11 -> 440000 | I11: =IF(C11="Antipaludéen",H11*30%,IF(C11="Antibiotique",H11*25%,H11*20%)) -> 110000 | J11: =IF(AND(E11>250,OR(D11="LABOREX",D11="COPHARMA")),"RÉAPPROVISIONNEMENT",IF(AND(E11>=150,E11<=250),"SURVEILLER","OK")) -> SURVEILLER | K11: =IFERROR(LEFT(UPPER(C11),3)&"/"&LEFT(A11,4)&"/"&LEFT(UPPER(D11),3),"ERR") -> ANT/MED0/BIO
A12: MED011 | B12: Zinc + Vitamine D | C12: Complément | D12: LABOREX | E12: 130 | F12: 1500 | G12: S4 | H12: =VENTES!$E12*VENTES!$F12 -> 195000 | I12: =IF(C12="Antipaludéen",H12*30%,IF(C12="Antibiotique",H12*25%,H12*20%)) -> 39000 | J12: =IF(AND(E12>250,OR(D12="LABOREX",D12="COPHARMA")),"RÉAPPROVISIONNEMENT",IF(AND(E12>=150,E12<=250),"SURVEILLER","OK")) -> OK | K12: =IFERROR(LEFT(UPPER(C12),3)&"/"&LEFT(A12,4)&"/"&LEFT(UPPER(D12),3),"ERR") -> COM/MED0/LAB
A13: MED012 | B13: Cotrimoxazole 480mg | C13: Antibiotique | D13: COPHARMED | E13: 170 | F13: 650 | G13: S4 | H13: =VENTES!$E13*VENTES!$F13 -> 110500 | I13: =IF(C13="Antipaludéen",H13*30%,IF(C13="Antibiotique",H13*25%,H13*20%)) -> 27625 | J13: =IF(AND(E13>250,OR(D13="LABOREX",D13="COPHARMA")),"RÉAPPROVISIONNEMENT",IF(AND(E13>=150,E13<=250),"SURVEILLER","OK")) -> SURVEILLER | K13: =IFERROR(LEFT(UPPER(C13),3)&"/"&LEFT(A13,4)&"/"&LEFT(UPPER(D13),3),"ERR") -> ANT/MED0/COP

Sheet ANALYSE
A1: TABLEAU DE BORD-PHARMACIE BAOBAB-JANVIER 2025
A2: Chiffre d'affaires total du mois | B2: =SUM(VENTES!H2:H13) -> 3172500
A3: CA total-Fournisseur LABOREX | B3: =SUMIF(VENTES!D2:D13,"LABOREX",VENTES!H2:H13) -> 1852500
A4: Quantité totale vendue | B4: =SUM(VENTES!E2:E13) -> 2690
A5: Nombre de médicaments à réapprovisionner | B5: =COUNTIF(VENTES!J2:J13,"RÉAPPROVISIONNEMENT") -> 4
A6: Marge brute totale | B6: =SUM(VENTES!I8:I13) -> 452825
A7: CA moyen par médicament | B7: =AVERAGE(VENTES!H2:H13) -> 264375
A14: FICHE DE CONSULTATION PAR CODE MÉDICAMENT
A15: Saisir le code médicament(ex: MED007) | B15: MED007
A16: Médicament | B16: =VLOOKUP($B$15,VENTES!$A$2:$K$13,2,0) -> Arteméter-Luméfantrine
A17: Catégorie | B17: =VLOOKUP($B$15,VENTES!$A$2:$K$13,3,0) -> Antipaludéen
A18: Fournisseur | B18: =VLOOKUP($B$15,VENTES!$A$2:$K$13,4,0) -> LABOREX
A19: Quantité vendue | B19: =VLOOKUP($B$15,VENTES!$A$2:$K$13,5,0) -> 320
A20: Prix unitaire | B20: =VLOOKUP($B$15,VENTES!$A$2:$K$13,6,0) -> 2500
A21: CA | B21: =VLOOKUP($B$15,VENTES!$A$2:$K$13,8,0) -> 800000
A22: Marge brute | B22: =VLOOKUP($B$15,VENTES!$A$2:$K$13,9,0) -> 240000
A23: Statut stock | B23: =VLOOKUP($B$15,VENTES!$A$2:$K$13,10,0) -> RÉAPPROVISIONNEMENT

Sheet GRAPHIQUE
